kwidgets/__init__.py
kwidgets/utils.py
kwidgets/dataviz/__init__.py
kwidgets/dataviz/boxplot.py
kwidgets/dataviz/math.py
kwidgets/text/__init__.py
kwidgets/text/labeledvalue.py
kwidgets/text/quotationdisplay.py
kwidgets/text/simpletable.py
kwidgets/uix/__init__.py
kwidgets/uix/pixelatedgrid.py
kwidgets/uix/radiobuttons.py
kwidgets-0.1.2.dist-info/LICENSE
kwidgets-0.1.2.dist-info/METADATA
kwidgets-0.1.2.dist-info/WHEEL
kwidgets-0.1.2.dist-info/top_level.txt
kwidgets-0.1.2.dist-info/RECORD
