Metadata-Version: 2.1
Name: kwidgets
Version: 0.1.2
Summary: Some generally useful widgets for kivy
Home-page: https://github.com/man-vs-electron/kwidgets
Author: Man vs Electron
Author-email: manvselectron@gmail.com
License: Apache Software License
Project-URL: Bug Tracker, https://github.com/man-vs-electron/kwidgets/issues
Platform: UNKNOWN
Classifier: Development Status :: 4 - Beta
Classifier: Topic :: Software Development :: User Interfaces
Classifier: License :: OSI Approved :: Apache Software License
Requires-Python: >=3.6
License-File: LICENSE
Requires-Dist: numpy
Requires-Dist: kivy (>=2)
